pyoframe/__init__.py
pyoframe/_arithmetic.py
pyoframe/_constants.py
pyoframe/_core.py
pyoframe/_model.py
pyoframe/_model_element.py
pyoframe/_monkey_patch.py
pyoframe/_objective.py
pyoframe/_param.py
pyoframe/_utils.py
pyoframe/_version.py
pyoframe-1.2.0.dist-info/licenses/LICENSE
pyoframe-1.2.0.dist-info/METADATA
pyoframe-1.2.0.dist-info/WHEEL
pyoframe-1.2.0.dist-info/top_level.txt
pyoframe-1.2.0.dist-info/RECORD
